setup.cfg
setup.py
ExVocabulary.egg-info/PKG-INFO
ExVocabulary.egg-info/SOURCES.txt
ExVocabulary.egg-info/dependency_links.txt
ExVocabulary.egg-info/requires.txt
ExVocabulary.egg-info/top_level.txt
exvocabulary/ExVocabulary.py
exvocabulary/__init__.py
exvocabulary.egg-info/SOURCES.txt
tests/__init__.py
tests/tests.py