Metadata-Version: 1.1
Name: exvocabulary
Version: 0.0.2
Summary: Module to get part_of_speech, synonym, antonym, vocabulary_example, and hyphenation for a given word. Extend from Vocabulary
Home-page: https://github.com/adavis10006/ExVocabulary
Author: Chen, Shang-Kuei
Author-email: adavis10006@gmail.com
License: MIT
Download-URL: https://github.com/adavis10006/ExVocabulary/tarball/master
Keywords: Dictionary,Vocabulary,simple dictionary,pydict,dictionary module
Platform: UNKNOWN
